ehk.py
ehk-1.2.1.dist-info/licenses/LICENSE
ehk-1.2.1.dist-info/METADATA
ehk-1.2.1.dist-info/WHEEL
ehk-1.2.1.dist-info/top_level.txt
ehk-1.2.1.dist-info/RECORD
