Metadata-Version: 2.4
Name: ehk
Version: 1.2.1
Summary: Türkçe temel matematik modülü
Home-page: https://pynet.neocities.org
Author: Eren
Author-email: dtb161616@gmail.com
Classifier: Programming Language :: Python :: 3
Classifier: License :: OSI Approved :: MIT License
Classifier: Operating System :: OS Independent
Requires-Python: >=3.6
License-File: LICENSE
Dynamic: author
Dynamic: author-email
Dynamic: classifier
Dynamic: description
Dynamic: description-content-type
Dynamic: home-page
Dynamic: license-file
Dynamic: requires-python
Dynamic: summary
